crs_linter/__init__.py
crs_linter/cli.py
crs_linter/lint_problem.py
crs_linter/linter.py
crs_linter/logger.py
crs_linter/rule.py
crs_linter/rules_metadata.py
crs_linter/utils.py
crs_linter/rules/approved_tags.py
crs_linter/rules/check_capture.py
crs_linter/rules/crs_tag.py
crs_linter/rules/deprecated.py
crs_linter/rules/duplicated.py
crs_linter/rules/ignore_case.py
crs_linter/rules/indentation.py
crs_linter/rules/lowercase_ignorecase.py
crs_linter/rules/ordered_actions.py
crs_linter/rules/pl_consistency.py
crs_linter/rules/rule_tests.py
crs_linter/rules/variables_usage.py
crs_linter/rules/version.py
crs_linter-1.0.0.dist-info/METADATA
crs_linter-1.0.0.dist-info/WHEEL
crs_linter-1.0.0.dist-info/entry_points.txt
crs_linter-1.0.0.dist-info/licenses/LICENSE
crs_linter-1.0.0.dist-info/RECORD
