Metadata-Version: 2.4
Name: crs-linter
Version: 1.0.0
Summary: CRS linter
Project-URL: issues, https://github.com/coreruleset/crs-linter/issues
Project-URL: homepage, https://github.com/coreruleset/crs-linter
Project-URL: repository, https://github.com/coreruleset/crs-linter.git
Author-email: Ervin Hegedus <airween@gmail.com>
License-Expression: Apache-2.0
License-File: LICENSE
Keywords: CRS,OWASP,linter
Classifier: License :: OSI Approved :: Apache Software License
Classifier: Operating System :: OS Independent
Classifier: Programming Language :: Python :: 3
Requires-Python: >=3.11
Requires-Dist: dulwich<0.26.0,>=0.25.0
Requires-Dist: github-action-utils<2.0.0,>=1.1.0
Requires-Dist: msc-pyparser>=1.2.1
Requires-Dist: semver<4.0.0,>=3.0.2
